MateMenus/__init__.py
MateMenus/buttons.py
MateMenus/generics.py
MateMenus/keyboards.py
MateMenus/panel_decorators.py
MateMenus/panels.py
MateWrapper/__init__.py
MateWrapper/bot.py
MateWrapper/context.py
MateWrapper/generics.py
MateWrapper/globals.py
MateWrapper/handlers.py
MateWrapper/prompts.py
MateWrapper/variables.py
mate_wrapper-1.2.1.dist-info/LICENSE
mate_wrapper-1.2.1.dist-info/METADATA
mate_wrapper-1.2.1.dist-info/WHEEL
mate_wrapper-1.2.1.dist-info/top_level.txt
mate_wrapper-1.2.1.dist-info/RECORD
