Metadata-Version: 2.1
Name: mate-wrapper
Version: 1.2.1
Summary: The Easy Telegram Application Maker
Home-page: https://github.com/SudoOmbro/MATE
Author: SudoOmbro
Author-email: ombroso1000@gmail.com
License: MIT
Classifier: License :: OSI Approved :: MIT License
Classifier: Programming Language :: Python :: 3.9
License-File: LICENSE
Requires-Dist: python-telegram-bot
